langgraph_checkpoint_cosmosdb/LICENSE
langgraph_checkpoint_cosmosdb/__init__.py
langgraph_checkpoint_cosmosdb/cosmosSerializer.py
langgraph_checkpoint_cosmosdb/cosmosdbSaver.py
langgraph_checkpoint_cosmosdb-0.2.5.dist-info/METADATA
langgraph_checkpoint_cosmosdb-0.2.5.dist-info/WHEEL
langgraph_checkpoint_cosmosdb-0.2.5.dist-info/RECORD
